fava_portfolio_returns/FavaPortfolioReturns.js
fava_portfolio_returns/__init__.py
fava_portfolio_returns/_vendor/beangrow.pyi
fava_portfolio_returns/_vendor/vendor.txt
fava_portfolio_returns/_vendor/beangrow/COPYING
fava_portfolio_returns/_vendor/beangrow/__init__.py
fava_portfolio_returns/_vendor/beangrow/compute_returns.py
fava_portfolio_returns/_vendor/beangrow/compute_returns_beam.py
fava_portfolio_returns/_vendor/beangrow/config.py
fava_portfolio_returns/_vendor/beangrow/config_pb2.py
fava_portfolio_returns/_vendor/beangrow/configure.py
fava_portfolio_returns/_vendor/beangrow/download_prices.py
fava_portfolio_returns/_vendor/beangrow/download_prices_from_file.py
fava_portfolio_returns/_vendor/beangrow/investments.py
fava_portfolio_returns/_vendor/beangrow/reports.py
fava_portfolio_returns/_vendor/beangrow/returns.py
fava_portfolio_returns/_vendor/beangrow/returns_test.py
fava_portfolio_returns/api/__init__.py
fava_portfolio_returns/api/cash_flows.py
fava_portfolio_returns/api/cash_flows_test.py
fava_portfolio_returns/api/compare.py
fava_portfolio_returns/api/compare_test.py
fava_portfolio_returns/api/investments.py
fava_portfolio_returns/api/investments_test.py
fava_portfolio_returns/api/portfolio.py
fava_portfolio_returns/api/portfolio_test.py
fava_portfolio_returns/core/currencies_test.py
fava_portfolio_returns/core/intervals.py
fava_portfolio_returns/core/intervals_test.py
fava_portfolio_returns/core/portfolio.py
fava_portfolio_returns/core/portfolio_test.py
fava_portfolio_returns/core/pricer.py
fava_portfolio_returns/core/pricer_test.py
fava_portfolio_returns/core/utils.py
fava_portfolio_returns/core/utils_test.py
fava_portfolio_returns/returns/__init__.py
fava_portfolio_returns/returns/base.py
fava_portfolio_returns/returns/factory.py
fava_portfolio_returns/returns/irr.py
fava_portfolio_returns/returns/irr_test.py
fava_portfolio_returns/returns/mdm.py
fava_portfolio_returns/returns/mdm_test.py
fava_portfolio_returns/returns/monetary.py
fava_portfolio_returns-2.4.0.dist-info/METADATA
fava_portfolio_returns-2.4.0.dist-info/WHEEL
fava_portfolio_returns-2.4.0.dist-info/licenses/COPYING
fava_portfolio_returns-2.4.0.dist-info/licenses/src/fava_portfolio_returns/_vendor/beangrow/COPYING
fava_portfolio_returns-2.4.0.dist-info/RECORD
