Metadata-Version: 2.4
Name: fava-portfolio-returns
Version: 2.4.0
Summary: fava-portfolio-returns shows portfolio returns in Fava
Project-URL: Source, https://github.com/andreasgerstmayr/fava-portfolio-returns
Project-URL: Issues, https://github.com/andreasgerstmayr/fava-portfolio-returns/issues
Project-URL: Changelog, https://github.com/andreasgerstmayr/fava-portfolio-returns/blob/main/CHANGELOG.md
Author-email: Andreas Gerstmayr <andreas@gerstmayr.me>
License: GPL-2.0
License-File: COPYING
License-File: src/fava_portfolio_returns/_vendor/beangrow/COPYING
Keywords: beancount,fava,investment,portfolio,returns
Classifier: Development Status :: 4 - Beta
Classifier: Intended Audience :: Financial and Insurance Industry
Classifier: Topic :: Office/Business :: Financial :: Accounting
Classifier: Topic :: Office/Business :: Financial :: Investment
Requires-Python: >=3.10
Requires-Dist: fava>=1.30.3
Requires-Dist: numpy>=1.26.4
Requires-Dist: pandas>=2.2.2
Requires-Dist: protobuf>=5.29.3
Requires-Dist: scipy>=1.13.1
